musicli_sequencer/__init__.py
musicli_sequencer/__main__.py
musicli_sequencer/interface.py
musicli_sequencer/main.py
musicli_sequencer/player.py
musicli_sequencer/song.py
musicli_sequencer-2.1.0.dist-info/entry_points.txt
musicli_sequencer-2.1.0.dist-info/licenses/LICENSE.txt
musicli_sequencer-2.1.0.dist-info/WHEEL
musicli_sequencer-2.1.0.dist-info/METADATA
musicli_sequencer-2.1.0.dist-info/RECORD
