Metadata-Version: 2.4
Name: musicli-sequencer
Version: 2.1.0
Summary: TUI MIDI sequencer
Author: Aaron Friesen
Classifier: License :: OSI Approved :: GNU General Public License v3 or later (GPLv3+)
License-File: LICENSE.txt
Requires-Dist: mido ~=1.3.3
Requires-Dist: pyfluidsynth ~=1.3.4
Project-URL: Changelog, https://github.com/friedev/musicli/blob/main/CHANGELOG.md
Project-URL: GitHub, https://github.com/friedev/musicli
Project-URL: Home, https://frie.dev/musicli
